linode_dynamic_dns.py
linode_dynamic_dns-0.7.0.dist-info/LICENSE
linode_dynamic_dns-0.7.0.dist-info/METADATA
linode_dynamic_dns-0.7.0.dist-info/WHEEL
linode_dynamic_dns-0.7.0.dist-info/entry_points.txt
linode_dynamic_dns-0.7.0.dist-info/top_level.txt
linode_dynamic_dns-0.7.0.dist-info/RECORD
