Metadata-Version: 2.1
Name: linode-dynamic-dns
Version: 0.7.0
Summary: Dynamically set the IP of Linode DNS records
Home-page: https://github.com/nvllsvm/linode-dynamic-dns
Author: Andrew Rabert
Author-email: ar@nullsum.net
License: MIT
License-File: LICENSE
